{
  "legislative_session": "2026",
  "identifier": "HB8059",
  "title": "AN ACT RELATING TO CRIMINAL OFFENSES -- GAMBLING AND LOTTERIES",
  "from_organization": "~{\"classification\": \"lower\"}",
  "classification": [
    "bill"
  ],
  "subject": [],
  "abstracts": [
    {
      "note": "summary",
      "abstract": "Allows nonprofit organizations to participate in permitted games of chance upon registering with the state police on an annual basis. The nonprofit would be exempt from any required background checks by local law enforcement."
    }
  ],
  "other_titles": [],
  "other_identifiers": [
    {
      "identifier": "ocd-bill-ri-2026-hb8059"
    }
  ],
  "actions": [
    {
      "description": "02/27/2026 Introduced, referred to House Judiciary",
      "date": "2026-02-27",
      "organization_id": "~{\"classification\": \"lower\"}",
      "classification": [
        "introduction",
        "referral-committee"
      ],
      "related_entities": [],
      "_processing": {
        "log_file_created": "2026-07-13T06:04:51Z"
      }
    },
    {
      "description": "03/20/2026 Scheduled for hearing and/or consideration  (03/24/2026)",
      "date": "2026-03-20",
      "organization_id": "~{\"classification\": \"legislature\"}",
      "classification": [],
      "related_entities": [],
      "_processing": {
        "log_file_created": "2026-07-13T06:04:51Z"
      }
    },
    {
      "description": "03/24/2026 Committee recommended measure be held for further study",
      "date": "2026-03-24",
      "organization_id": "~{\"classification\": \"legislature\"}",
      "classification": [
        "committee-failure"
      ],
      "related_entities": [],
      "_processing": {
        "log_file_created": "2026-07-13T06:04:51Z"
      }
    }
  ],
  "sponsorships": [
    {
      "name": "Casey",
      "classification": "primary",
      "entity_type": "person",
      "primary": true,
      "person_id": "~{\"name\": \"Casey\"}",
      "organization_id": null
    },
    {
      "name": "Phillips",
      "classification": "primary",
      "entity_type": "person",
      "primary": true,
      "person_id": "~{\"name\": \"Phillips\"}",
      "organization_id": null
    },
    {
      "name": "Hopkins",
      "classification": "primary",
      "entity_type": "person",
      "primary": true,
      "person_id": "~{\"name\": \"Hopkins\"}",
      "organization_id": null
    },
    {
      "name": "O'Brien",
      "classification": "primary",
      "entity_type": "person",
      "primary": true,
      "person_id": "~{\"name\": \"O'Brien\"}",
      "organization_id": null
    },
    {
      "name": "Dawson",
      "classification": "primary",
      "entity_type": "person",
      "primary": true,
      "person_id": "~{\"name\": \"Dawson\"}",
      "organization_id": null
    },
    {
      "name": "Read",
      "classification": "primary",
      "entity_type": "person",
      "primary": true,
      "person_id": "~{\"name\": \"Read\"}",
      "organization_id": null
    },
    {
      "name": "Corvese",
      "classification": "primary",
      "entity_type": "person",
      "primary": true,
      "person_id": "~{\"name\": \"Corvese\"}",
      "organization_id": null
    },
    {
      "name": "Biah",
      "classification": "primary",
      "entity_type": "person",
      "primary": true,
      "person_id": "~{\"name\": \"Biah\"}",
      "organization_id": null
    },
    {
      "name": "Azzinaro",
      "classification": "primary",
      "entity_type": "person",
      "primary": true,
      "person_id": "~{\"name\": \"Azzinaro\"}",
      "organization_id": null
    },
    {
      "name": "Place",
      "classification": "primary",
      "entity_type": "person",
      "primary": true,
      "person_id": "~{\"name\": \"Place\"}",
      "organization_id": null
    }
  ],
  "related_bills": [],
  "versions": [
    {
      "note": "8059",
      "links": [
        {
          "url": "http://webserver.rilegislature.gov/BillText/BillText26/HouseText26/H8059.pdf",
          "media_type": "application/pdf"
        }
      ],
      "date": "",
      "classification": ""
    }
  ],
  "documents": [],
  "citations": [],
  "sources": [
    {
      "url": "https://status.rilegislature.gov/",
      "note": ""
    }
  ],
  "extras": {},
  "jurisdiction": {
    "id": "ocd-jurisdiction/country:us/state:ri/government",
    "name": "Rhode Island",
    "classification": "state",
    "division_id": "ocd-division/country:us/state:ri"
  },
  "_processing": {
    "logs_latest_update": "2026-07-13T06:04:51Z"
  }
}